sphinx_nostalgistjs/__init__.py
sphinx_nostalgistjs-1.0.3.dist-info/LICENSE
sphinx_nostalgistjs-1.0.3.dist-info/METADATA
sphinx_nostalgistjs-1.0.3.dist-info/WHEEL
sphinx_nostalgistjs-1.0.3.dist-info/top_level.txt
sphinx_nostalgistjs-1.0.3.dist-info/RECORD
