Metadata-Version: 2.1
Name: sphinx-nostalgistjs
Version: 1.0.3
Summary: Sphinx extension for embeding Isso comments in documents
Author: Lucas Pires Camargo
Maintainer: Lucas Pires Camargo
Project-URL: homepage, https://camargo.eng.br/projects/sphinx-nostalgistjs/README.html
Project-URL: repository, https://github.com/lucaspcamargo/sphinx-nostalgistjs
Project-URL: tracker, https://github.com/lucaspcamargo/sphinx-nostalgistjs/issues
Keywords: documentation,sphinx,extension,nostalgistjs,emulation,games
Classifier: Environment :: Plugins
Classifier: Framework :: Sphinx
Classifier: Framework :: Sphinx :: Extension
Classifier: License :: OSI Approved :: GNU General Public License v3 (GPLv3)
Classifier: Operating System :: OS Independent
Classifier: Programming Language :: Python
Classifier: Programming Language :: Python :: 3
Classifier: Topic :: Documentation
Classifier: Topic :: Documentation :: Sphinx
Classifier: Topic :: Games/Entertainment
Classifier: Topic :: Games/Entertainment :: Arcade
Requires-Python: >=3.10
License-File: LICENSE
Requires-Dist: Sphinx>=4
